scons_compiledb/__init__.py
scons_compiledb/cmdline.py
scons_compiledb/core.py
scons_compiledb/entry_func.py
scons_compiledb-0.7.4.dist-info/LICENSE
scons_compiledb-0.7.4.dist-info/METADATA
scons_compiledb-0.7.4.dist-info/WHEEL
scons_compiledb-0.7.4.dist-info/top_level.txt
scons_compiledb-0.7.4.dist-info/RECORD
